pydx/__init__.py
pydx/pydx.py
pydx/engine/__init__.py
pydx/engine/helpers.py
pydx/engine/plugin_engine.py
pydx/sfdc/__init__.py
pydx/sfdc/exceptions.py
pydx/sfdc/sfdc.py
pydx/sfdc/soap_messages.py
pydx/standard_plugins/__init__.py
pydx/standard_plugins/standard_plugins.py
pydx/utils/__init__.py
pydx/utils/sfdc_utils.py
Python_SFDX_Toolkit-0.0.4.dist-info/METADATA
Python_SFDX_Toolkit-0.0.4.dist-info/WHEEL
Python_SFDX_Toolkit-0.0.4.dist-info/entry_points.txt
Python_SFDX_Toolkit-0.0.4.dist-info/top_level.txt
Python_SFDX_Toolkit-0.0.4.dist-info/RECORD
