Metadata-Version: 2.1
Name: Python-SFDX-Toolkit
Version: 0.0.4
Summary: Python SFDX Toolkit
Home-page: https://github.com/lnapo94/Python-SFDX-Tool
Author: Luca Napoletano
Author-email: lnapo94@gmail.com
License: MIT
Platform: UNKNOWN
Requires-Python: >=3.9
Requires-Dist: click (==8.1.3)
Requires-Dist: requests (==2.27.1)
Requires-Dist: yaspin (==2.1.0)
Requires-Dist: beautifulsoup4 (==4.11.1)
Requires-Dist: lxml (==4.8.0)
Requires-Dist: xmltodict (==0.13.0)
